uw_zoom/VERSION
uw_zoom/__init__.py
uw_zoom/accounts.py
uw_zoom/dao.py
uw_zoom/exceptions.py
uw_zoom/models.py
uw_zoom/test.py
uw_zoom/users.py
uw_zoom/utilities.py
uw_zoom/resources/zoom/file/v2/accounts?page_size=300
uw_zoom/resources/zoom/file/v2/users?page_size=300
uw_zoom/resources/zoom/file/v2/users?page_size=300&page_number=2
uw_zoom/resources/zoom/file/v2/users/z8yAAAAA8bbbQ/index.html
uw_zoom/resources/zoom/file/v2/users/z8yAAAAA8bbbQ/settings
uw_zoom/tests/__init__.py
uw_zoom/tests/test_accounts.py
uw_zoom/tests/test_users.py
uw_zoom/tests/test_zoom.py
UW_RestClients_Zoom-0.1.7.dist-info/LICENSE
UW_RestClients_Zoom-0.1.7.dist-info/METADATA
UW_RestClients_Zoom-0.1.7.dist-info/WHEEL
UW_RestClients_Zoom-0.1.7.dist-info/top_level.txt
UW_RestClients_Zoom-0.1.7.dist-info/RECORD
