Metadata-Version: 2.1
Name: UW-RestClients-Zoom
Version: 0.1.7
Summary: A library for connecting to Zoom at the University of Washington
Home-page: https://github.com/uw-it-aca/uw-restclients-zoom
Author: UW-IT AXDD
Author-email: aca-it@uw.edu
License: Apache License, Version 2.0
Platform: UNKNOWN
Classifier: Intended Audience :: Developers
Classifier: License :: OSI Approved :: Apache Software License
Classifier: Operating System :: OS Independent
Classifier: Programming Language :: Python
Classifier: Programming Language :: Python :: 3.6
Requires-Dist: UW-RestClients-Core
Requires-Dist: PyJWT
Requires-Dist: python-dateutil
Requires-Dist: pytz
Requires-Dist: mock
